avi_r/__init__.py
avi_r/frame.py
avi_r/reader.py
avi_r/utils.py
avi_r-1.3.9.dist-info/LICENSE
avi_r-1.3.9.dist-info/METADATA
avi_r-1.3.9.dist-info/WHEEL
avi_r-1.3.9.dist-info/top_level.txt
avi_r-1.3.9.dist-info/RECORD
