Metadata-Version: 2.1
Name: avi-r
Version: 1.3.9
Summary: A robust reader for avi videos.
Home-page: https://github.com/CMU-INF-DIVA/avi-r
Author: Lijun Yu
Author-email: lijun@lj-y.com
License: GPL
Platform: UNKNOWN
Requires-Python: >=3.6
Requires-Dist: numpy
Requires-Dist: av (>=8.0)
